{
    "name": "HC-LIB.IO",
    "version": "1.0.2111",
    "description": "This library is a tool to help the programmer to work with I/O Ports on the Arduino Board.",
    "keywords": "io, arduino, atmelavr",
    "repository":
    {
      "type": "git",
      "url": "https://github.com/romango78/HC-LIB/tree/main/io-lib"
    },
    "authors":
    [
      {
        "name": "Roman Gorielov",
        "email": "romango78@gmail.com"        
      }
    ],
    "dependencies":
    [
      {
        "name": "HC-LIB.System",
        "version": ">=1.0.2111"
      }
    ],    
    "license": "MIT",    
    "frameworks": "*",
    "platforms": ["atmelavr"]
  }